polars_pbv-0.1.0.dist-info/METADATA
polars_pbv-0.1.0.dist-info/WHEEL
polars_pbv/__init__.py
polars_pbv/utils.py
polars_pbv/polars_pbv.abi3.so
polars_pbv-0.1.0.dist-info/RECORD
